mpnum/__init__.py
mpnum/_named_ndarray.py
mpnum/_testing.py
mpnum/factory.py
mpnum/linalg.py
mpnum/mparray.py
mpnum/mpsmpo.py
mpnum/mpstruct.py
mpnum/special.py
mpnum/povm/__init__.py
mpnum/povm/localpovm.py
mpnum/povm/mppovm.py
mpnum/utils/__init__.py
mpnum/utils/array_transforms.py
mpnum/utils/extmath.py
mpnum/utils/physics.py
mpnum/utils/pmf.py
mpnum-1.0.2.dist-info/DESCRIPTION.rst
mpnum-1.0.2.dist-info/METADATA
mpnum-1.0.2.dist-info/RECORD
mpnum-1.0.2.dist-info/WHEEL
mpnum-1.0.2.dist-info/metadata.json
mpnum-1.0.2.dist-info/top_level.txt
