Metadata-Version: 2.0
Name: mpnum
Version: 1.0.2
Summary: matrix product representation library
Home-page: https://github.com/dseuss/mpnum
Author: Daniel Suess, Milan Holzäpfel
Author-email: daniel@dsuess.me, mail@mjh.name
License: BSD
Platform: ALL
Classifier: Development Status :: 4 - Beta
Classifier: Operating System :: OS Independent
Classifier: License :: OSI Approved :: BSD License
Classifier: Programming Language :: Python :: 2.7
Classifier: Programming Language :: Python :: 3.4
Classifier: Programming Language :: Python :: 3.5
Classifier: Programming Language :: Python :: 3.6
Classifier: Intended Audience :: Science/Research
Requires-Dist: SciPy (>=0.15)
Requires-Dist: NumPy (>=1.5.1)
Requires-Dist: six (>=1.0)
